amasel/__init__.py
amasel/extract.py
amasel-2.3.7.1.dist-info/METADATA
amasel-2.3.7.1.dist-info/WHEEL
amasel-2.3.7.1.dist-info/licence
amasel-2.3.7.1.dist-info/top_level.txt
amasel-2.3.7.1.dist-info/RECORD
