Metadata-Version: 2.1
Name: amasel
Version: 2.3.7.1
Summary: A package to scrape Amazon product description using Selenium.
Author: Shamim Mahbub
Author-email: sha237mim@gmail.com
Keywords: python,amazon_scrape,selenium
Classifier: Development Status :: 1 - Planning
Classifier: Intended Audience :: Developers
Classifier: Programming Language :: Python :: 3
Classifier: Operating System :: Unix
Classifier: Operating System :: MacOS :: MacOS X
Classifier: Operating System :: Microsoft :: Windows
License-File: licence
Requires-Dist: selenium
